JWTLibrary/__init__.py
JWTLibrary/cli.py
JWTLibrary/constants.py
JWTLibrary/exceptions.py
JWTLibrary/jwt_library.py
JWTLibrary/utils.py
JWTLibrary/version.py
JWTLibrary/keywords/__init__.py
JWTLibrary/keywords/token_decoding.py
JWTLibrary/keywords/token_generation.py
JWTLibrary/keywords/token_validation.py
JWTLibrary/keywords/utilities.py
robotframework_jwtlibrary-1.0.0.dist-info/METADATA
robotframework_jwtlibrary-1.0.0.dist-info/WHEEL
robotframework_jwtlibrary-1.0.0.dist-info/top_level.txt
robotframework_jwtlibrary-1.0.0.dist-info/RECORD
