Metadata-Version: 2.4
Name: robotframework-jwtlibrary
Version: 1.0.0
Summary: JWT Library for Robot Framework
Home-page: https://github.com/ohmrefresh/robotframework-jwtlibrary
Author: Your Name
Author-email: Your Name <your.email@example.com>
License: Apache-2.0
Project-URL: Homepage, https://github.com/ohmrefresh/robotframework-jwtlibrary
Project-URL: Documentation, https://jwt-robotframework-library.readthedocs.io/
Project-URL: Repository, https://github.com/ohmrefresh/robotframework-jwtlibrary.git
Project-URL: Bug Tracker, https://github.com/ohmrefresh/robotframework-jwtlibrary/issues
Classifier: Development Status :: 4 - Beta
Classifier: Intended Audience :: Developers
Classifier: Topic :: Software Development :: Testing
Classifier: License :: OSI Approved :: Apache Software License
Classifier: Programming Language :: Python :: 3
Classifier: Framework :: Robot Framework :: Library
Requires-Python: >=3.7
Requires-Dist: PyJWT>=2.0.0
Requires-Dist: robotframework>=4.0.0
Provides-Extra: dev
Requires-Dist: pytest>=6.0.0; extra == "dev"
Requires-Dist: pytest-cov>=2.10.0; extra == "dev"
Requires-Dist: black>=21.0.0; extra == "dev"
Requires-Dist: flake8>=3.8.0; extra == "dev"
Requires-Dist: mypy>=0.800; extra == "dev"
Requires-Dist: robotframework-lint>=1.1; extra == "dev"
Provides-Extra: docs
Requires-Dist: sphinx>=4.0.0; extra == "docs"
Requires-Dist: sphinx-rtd-theme>=0.5.0; extra == "docs"
Requires-Dist: myst-parser>=0.15.0; extra == "docs"
Provides-Extra: crypto
Requires-Dist: cryptography>=3.0.0; extra == "crypto"
Dynamic: author
Dynamic: home-page
Dynamic: requires-python
